fastrequest/__init__.py
fastrequest/http.cpython-37m-darwin.so
fastrequest-1.6.3b0.dist-info/LICENSE
fastrequest-1.6.3b0.dist-info/METADATA
fastrequest-1.6.3b0.dist-info/WHEEL
fastrequest-1.6.3b0.dist-info/top_level.txt
fastrequest-1.6.3b0.dist-info/RECORD
