Metadata-Version: 2.1
Name: fastrequest
Version: 1.6.3b0
Summary: fastrequest fast http requests extension
Home-page: https://github.com/ozansz/fastrequest
Author: Ozan Sazak
Author-email: ozan.sazak@protonmail.ch
License: UNKNOWN
Platform: UNKNOWN
Classifier: Programming Language :: Python :: 3
Classifier: License :: OSI Approved :: MIT License
Classifier: Operating System :: OS Independent
Requires-Python: >=3
